TensorflowImageHelperCD/cnn/ProgramFive.py
TensorflowImageHelperCD/cnn/ProgramFour.py
TensorflowImageHelperCD/cnn/ProgramOne.py
TensorflowImageHelperCD/cnn/ProgramSeven.py
TensorflowImageHelperCD/cnn/ProgramSix.py
TensorflowImageHelperCD/cnn/ProgramThree.py
TensorflowImageHelperCD/cnn/ProgramTwo.py
TensorflowImageHelperCD/cnn/__init__.py
TensorflowImageHelperCD/cnn/main.py
TensorflowImageHelperCD/dip/ProgramEight.py
TensorflowImageHelperCD/dip/ProgramFive.py
TensorflowImageHelperCD/dip/ProgramFour.py
TensorflowImageHelperCD/dip/ProgramOne.py
TensorflowImageHelperCD/dip/ProgramSeven.py
TensorflowImageHelperCD/dip/ProgramSix.py
TensorflowImageHelperCD/dip/ProgramThree.py
TensorflowImageHelperCD/dip/ProgramTwo.py
TensorflowImageHelperCD/dip/__init__.py
TensorflowImageHelperCD/dip/main.py
TensorflowImageHelperCD-0.2.0.dist-info/METADATA
TensorflowImageHelperCD-0.2.0.dist-info/WHEEL
TensorflowImageHelperCD-0.2.0.dist-info/top_level.txt
TensorflowImageHelperCD-0.2.0.dist-info/RECORD
